compatibility.py
main.py
setup.py
streamcollector.py
streamexecutor.py
streampy.py
tests.py
streampy.egg-info/PKG-INFO
streampy.egg-info/SOURCES.txt
streampy.egg-info/dependency_links.txt
streampy.egg-info/not-zip-safe
streampy.egg-info/top_level.txt