Metadata-Version: 1.0
Name: streampy
Version: 1.2
Summary: Java like stream pipelines, supports parallel operations
Home-page: https://github.com/tolsac/streampy.git
Author: Camille Tolsa
Author-email: camille.tolsa@gmail.com
License: MIT
Platform: UNKNOWN
